{
  "topics": [
    {
      "id": 1,
      "name": "শিক্ষা",
      "name_en": "Education",
      "faqs": [
        {
          "id": 1,
          "question": "একটি ভালো শিক্ষা প্রতিষ্ঠান কীভাবে নির্বাচন করা উচিত?",
          "answer": "একটি ভালো শিক্ষা প্রতিষ্ঠান নির্বাচনের জন্য নিম্নলিখিত বিষয়গুলি বিবেচনা করুন: শিক্ষকদের যোগ্যতা, শিক্ষার মান, অবস্থান, খরচ, অবকাঠামো এবং অতীতের সাফল্যের রেকর্ড। অভিভাবক এবং শিক্ষার্থীদের মতামত অত্যন্ত গুরুত্বপূর্ণ।",
          "topic": "শিক্ষা",
          "difficulty": "মাঝারি"
        },
        {
          "id": 2,
          "question": "অনলাইন শিক্ষা কি সত্যিই কার্যকর?",
          "answer": "হ্যাঁ, অনলাইন শিক্ষা অত্যন্ত কার্যকর হতে পারে যখন এটি সঠিকভাবে পরিচালিত হয়। এটি নমনীয়তা প্রদান করে, বৈশ্বিক সম্পদে অ্যাক্সেস দেয় এবং স্ব-গতিতে শেখার অনুমতি দেয়। তবে, শিক্ষার্থীদের স্ব-শৃঙ্খলা এবং মনোযোগের প্রয়োজন।",
          "topic": "শিক্ষা",
          "difficulty": "মাঝারি"
        },
        {
          "id": 3,
          "question": "স্টাডি করার সেরা পদ্ধতি কী?",
          "answer": "কার্যকর পড়াশোনার জন্য: নিয়মিত সময়সূচী তৈরি করুন, একটি শান্ত পরিবেশ খুঁজুন, অক্রিয় পড়ার বদলে সক্রিয় পড়াশোনা করুন, নিয়মিত পরীক্ষা নিন এবং প্রয়োজনে সাহায্য চান। পোমোডোরো টেকনিক ব্যবহার করাও কার্যকর।",
          "topic": "শিক্ষা",
          "difficulty": "সহজ"
        }
      ]
    },
    {
      "id": 2,
      "name": "স্বাস্থ্য",
      "name_en": "Health",
      "faqs": [
        {
          "id": 1,
          "question": "প্রতিদিন কতটা পানি পানো উচিত?",
          "answer": "সাধারণত একজন প্রাপ্তবয়স্ক ব্যক্তির প্রতিদিন কমপক্ষে ৮-১০ গ্লাস (২-৩ লিটার) পানি পানো উচিত। তবে এটি আপনার বয়স, কার্যকলাপ স্তর এবং জলবায়ু অনুযায়ী পরিবর্তিত হতে পারে।",
          "topic": "স্বাস্থ্য",
          "difficulty": "সহজ"
        },
        {
          "id": 2,
          "question": "সুস্থ থাকার জন্য কী করা উচিত?",
          "answer": "সুস্থ থাকার জন্য: নিয়মিত ব্যায়াম করুন, স্বাস্থ্যকর খাবার খান, পর্যাপ্ত ঘুম নিন, মানসিক চাপ কমান, নিয়মিত চেকআপ করান এবং ক্ষতিকর অভ্যাস এড়ান।",
          "topic": "স্বাস্থ্য",
          "difficulty": "মাঝারি"
        },
        {
          "id": 3,
          "question": "মানসিক স্বাস্থ্য কেন গুরুত্বপূর্ণ?",
          "answer": "মানসিক স্বাস্থ্য শারীরিক স্বাস্থ্যের মতোই গুরুত্বপূর্ণ। এটি আমাদের আবেগ, চিন্তাভাবনা এবং আচরণকে প্রভাবিত করে। ভালো মানসিক স্বাস্থ্য সম্পর্ক, কর্মক্ষমতা এবং সামগ্রিক জীবনযাত্রার মান উন্নত করে।",
          "topic": "স্বাস্থ্য",
          "difficulty": "মাঝারি"
        }
      ]
    },
    {
      "id": 3,
      "name": "ভ্রমণ",
      "name_en": "Travel",
      "faqs": [
        {
          "id": 1,
          "question": "ভ্রমণের জন্য সেরা মৌসুম কোনটি?",
          "answer": "বাংলাদেশে অক্টোবর থেকে মার্চ সবচেয়ে ভালো সময়। এন্ত কম বৃষ্টি এবং আরামদায়ক তাপমাত্রা থাকে। গ্রীষ্মকাল গরম এবং বর্ষাকাল আর্দ্র হয়।",
          "topic": "ভ্রমণ",
          "difficulty": "সহজ"
        },
        {
          "id": 2,
          "question": "ভ্রমণ বাজেট কীভাবে পরিকল্পনা করা যায়?",
          "answer": "ভ্রমণ বাজেট পরিকল্পনার জন্য: পরিবহন, থাকা-খাওয়া, পর্যটন এবং অনাবশ্যক খরচের জন্য অনুমান করুন। স্থানীয় ম্যাপিং অ্যাপ ব্যবহার করুন, সাশ্রয়ী থাকার ব্যবস্থা খুঁজুন এবং আগে থেকে বুক করুন।",
          "topic": "ভ্রমণ",
          "difficulty": "মাঝারি"
        },
        {
          "id": 3,
          "question": "ভ্রমণকালে কী কী জিনিস নিয়ে যাওয়া উচিত?",
          "answer": "গুরুত্বপূর্ণ জিনিস: পাসপোর্ট/আইডি, টাকা/কার্ড, ওষুধ, পোশাক, টুথব্রাশ, সানস্ক্রিন, জরুরি যোগাযোগ তথ্য এবং ভ্রমণ ডকুমেন্ট। পরিবেশ অনুযায়ী জিনিস যুক্ত করুন।",
          "topic": "ভ্রমণ",
          "difficulty": "সহজ"
        }
      ]
    },
    {
      "id": 4,
      "name": "প্রযুক্তি",
      "name_en": "Technology",
      "faqs": [
        {
          "id": 1,
          "question": "কৃত্রিম বুদ্ধিমত্তা কী এবং এটি কীভাবে কাজ করে?",
          "answer": "কৃত্রিম বুদ্ধিমত্তা (AI) হল মেশিনগুলিকে মানুষের মতো কাজ করার জন্য প্রোগ্রাম করা। এটি মেশিন লার্নিং এবং গভীর শেখার মাধ্যমে ডেটা থেকে শিখে এবং ভবিষ্যতের সিদ্ধান্ত নেয়।",
          "topic": "প্রযুক্তি",
          "difficulty": "মাঝারি"
        },
        {
          "id": 2,
          "question": "সাইবার নিরাপত্তা কেন গুরুত্বপূর্ণ?",
          "answer": "সাইবার নিরাপত্তা ব্যক্তিগত তথ্য, আর্থিক ডেটা এবং ডিজিটাল সম্পদ রক্ষা করে। হ্যাকিং, ম্যালওয়্যার এবং ফিশিং থেকে রক্ষা করার জন্য শক্তিশালী পাসওয়ার্ড এবং আপডেট ব্যবহার করুন।",
          "topic": "প্রযুক্তি",
          "difficulty": "মাঝারি"
        },
        {
          "id": 3,
          "question": "ক্লাউড স্টোরেজ নিরাপদ কি?",
          "answer": "বেশিরভাগ নামকরা ক্লাউড সেবা প্রদানকারী শক্তিশালী এনক্রিপশন ব্যবহার করে। তবে, শক্তিশালী পাসওয়ার্ড সেট করুন, দুই-ফ্যাক্টর যাচাইকরণ সক্ষম করুন এবং সংবেদনশীল তথ্যের জন্য অতিরিক্ত সতর্কতা নিন।",
          "topic": "প্রযুক্তি",
          "difficulty": "মাঝারি"
        }
      ]
    },
    {
      "id": 5,
      "name": "খেলাধুলা",
      "name_en": "Sports",
      "faqs": [
        {
          "id": 1,
          "question": "নিয়মিত খেলাধুলা করার উপকার কী?",
          "answer": "খেলাধুলার উপকার: শারীরিক সুস্থতা বৃদ্ধি, হৃদয় মজবুত করা, মানসিক চাপ কমানো, আত্মবিশ্বাস বাড়ানো, ওজন নিয়ন্ত্রণ এবং দলগত দক্ষতা উন্নত করা।",
          "topic": "খেলাধুলা",
          "difficulty": "সহজ"
        },
        {
          "id": 2,
          "question": "ক্রীড়া আঘাত কীভাবে প্রতিরোধ করা যায়?",
          "answer": "ক্রীড়া আঘাত প্রতিরোধের জন্য: ওয়ার্মিং আপ করুন, সঠিক কৌশল শিখুন, উপযুক্ত সরঞ্জাম ব্যবহার করুন, ধীরে ধীরে প্রশিক্ষণ বাড়ান এবং শরীরকে বিশ্রামের সময় দিন।",
          "topic": "খেলাধুলা",
          "difficulty": "মাঝারি"
        },
        {
          "id": 3,
          "question": "ফুটবল খেলতে শিখতে চাই, শুরু কোথা থেকে?",
          "answer": "ফুটবল শুরু করার জন্য: স্থানীয় ক্লাব বা কোচ খুঁজুন, বেসিক দক্ষতা (ড্রিবলিং, পাসিং) অনুশীলন করুন, ভালো জুতা এবং পোশাক পান, অন্যদের সাথে খেলুন এবং নিয়মিত অনুশীলন করুন।",
          "topic": "খেলাধুলা",
          "difficulty": "সহজ"
        }
      ]
    }
  ]
}
